chist.py
setup.py
inspect_csv.egg-info/PKG-INFO
inspect_csv.egg-info/SOURCES.txt
inspect_csv.egg-info/dependency_links.txt
inspect_csv.egg-info/entry_points.txt
inspect_csv.egg-info/requires.txt
inspect_csv.egg-info/top_level.txt