Metadata-Version: 1.0
Name: inspect-csv
Version: 0.0.1
Summary: some simple CSV tools for summarizing tabular data.
Home-page: UNKNOWN
Author: Nicholas Del Grosso
Author-email: delgrosso.nick@gmail.com
License: UNKNOWN
Platform: UNKNOWN
